JsMacrosAC/AboutOverlay.py
JsMacrosAC/AbstractHorseEntityHelper.py
JsMacrosAC/AbstractMapSettingContainer.py
JsMacrosAC/AbstractMapSettingContainer_MapSettingEntry.py
JsMacrosAC/AbstractPiglinEntityHelper.py
JsMacrosAC/AbstractRenderCodeCompiler.py
JsMacrosAC/AbstractSettingContainer.py
JsMacrosAC/AbstractSettingField.py
JsMacrosAC/AbstractWidgetBuilder.py
JsMacrosAC/AdvancementHelper.py
JsMacrosAC/AdvancementManagerHelper.py
JsMacrosAC/AdvancementProgressHelper.py
JsMacrosAC/Alignable.py
JsMacrosAC/AllayEntityHelper.py
JsMacrosAC/AndFilter.py
JsMacrosAC/AnimalEntityHelper.py
JsMacrosAC/AnnotatedCheckBox.py
JsMacrosAC/AnvilInventory.py
JsMacrosAC/AreaEffectCloudEntityHelper.py
JsMacrosAC/ArmorStandEntityHelper.py
JsMacrosAC/ArrowEntityHelper.py
JsMacrosAC/AutoCompleteSuggester.py
JsMacrosAC/AutoCompleteSuggestion.py
JsMacrosAC/AxolotlEntityHelper.py
JsMacrosAC/BaseEvent.py
JsMacrosAC/BaseEventRegistry.py
JsMacrosAC/BaseHelper.py
JsMacrosAC/BaseLanguage.py
JsMacrosAC/BaseLibrary.py
JsMacrosAC/BaseListener.py
JsMacrosAC/BaseProfile.py
JsMacrosAC/BaseScreen.py
JsMacrosAC/BaseScriptContext.py
JsMacrosAC/BaseScriptContext_ScriptAssertionError.py
JsMacrosAC/BaseScriptContext_SleepRunnable.py
JsMacrosAC/BaseWrappedException.py
JsMacrosAC/BaseWrappedException_GuestLocation.py
JsMacrosAC/BaseWrappedException_HostLocation.py
JsMacrosAC/BaseWrappedException_SourceLocation.py
JsMacrosAC/BasicFilter.py
JsMacrosAC/BatEntityHelper.py
JsMacrosAC/BeaconInventory.py
JsMacrosAC/BeeEntityHelper.py
JsMacrosAC/BlazeEntityHelper.py
JsMacrosAC/BlockDataHelper.py
JsMacrosAC/BlockDisplayEntityHelper.py
JsMacrosAC/BlockFilter.py
JsMacrosAC/BlockHelper.py
JsMacrosAC/BlockPosHelper.py
JsMacrosAC/BlockPredicateHelper.py
JsMacrosAC/BlockStateFilter.py
JsMacrosAC/BlockStateHelper.py
JsMacrosAC/BoatEntityHelper.py
JsMacrosAC/BooleanCompareFilter.py
JsMacrosAC/BooleanField.py
JsMacrosAC/BossBarConsumer.py
JsMacrosAC/BossBarHelper.py
JsMacrosAC/Box.py
JsMacrosAC/Box_Builder.py
JsMacrosAC-1.9.2.5550893.dist-info/METADATA
JsMacrosAC-1.9.2.5550893.dist-info/WHEEL
JsMacrosAC-1.9.2.5550893.dist-info/top_level.txt
JsMacrosAC-1.9.2.5550893.dist-info/RECORD
