Metadata-Version: 2.1
Name: JsMacrosAC
Version: 1.9.2.5550893
Summary: A package to let your IDE know what JsMacros can do
Home-page: UNKNOWN
Author: Hasenzahn1
Author-email: <motzer10@gmx.de>
License: UNKNOWN
Keywords: python,JsMacros,Autocomplete,Doc
Platform: UNKNOWN
Classifier: Intended Audience :: Developers
Classifier: Programming Language :: Python :: 3
Classifier: Operating System :: Unix
Classifier: Operating System :: MacOS :: MacOS X
Classifier: Operating System :: Microsoft :: Windows
